lemay_ai_sidecar/__init__.py
lemay_ai_sidecar/lemay_ai_sidecar.py
lemay_ai_sidecar-0.0.1.dist-info/METADATA
lemay_ai_sidecar-0.0.1.dist-info/RECORD
lemay_ai_sidecar-0.0.1.dist-info/WHEEL
lemay_ai_sidecar-0.0.1.dist-info/top_level.txt
